dlroWolleH/__init__.py
dlroWolleH/dlroWolleH.py
dlroWolleH-0.0.1.dist-info/LICENSE
dlroWolleH-0.0.1.dist-info/METADATA
dlroWolleH-0.0.1.dist-info/WHEEL
dlroWolleH-0.0.1.dist-info/top_level.txt
dlroWolleH-0.0.1.dist-info/RECORD
