Metadata-Version: 2.1
Name: dlroWolleH
Version: 0.0.1
Summary: !dlroWolleH
Home-page: UNKNOWN
Author: sakkyoi
License: UNKNOWN
Platform: UNKNOWN
